Metadata-Version: 2.1
Name: scipybiteopt
Version: 1.2
Summary: Scipy style wrapper for Aleksey Vaneev's BiteOpt
Home-page: https://github.com/dschmitz89/scipybiteopt
Author: dschmitz89
Author-email: danielschmitzsiegen@gmail.com
License: MIT
Platform: UNKNOWN
